workflow_builder/__init__.py
workflow_builder/configuration.py
workflow_builder/logger.py
workflow_builder/utils.py
workflow_builder/workflow.py
workflow_builder-0.11.dist-info/METADATA
workflow_builder-0.11.dist-info/WHEEL
workflow_builder-0.11.dist-info/top_level.txt
workflow_builder-0.11.dist-info/RECORD
