Metadata-Version: 2.1
Name: workflow_builder
Version: 0.11
Summary: A tool for building and executing workflows
Home-page: https://github.com/Ifilk/WorkflowBuilder
Author: Ifilk
Author-email: suanxc@yeah.net
Requires-Python: >=3.6
Requires-Dist: toml
